kozmoai/version/__init__.py
kozmoai/version/version.py
kozmoai-1.2.0.dev0.dist-info/METADATA
kozmoai-1.2.0.dev0.dist-info/WHEEL
kozmoai-1.2.0.dev0.dist-info/entry_points.txt
kozmoai-1.2.0.dev0.dist-info/licenses/LICENSE
kozmoai-1.2.0.dev0.dist-info/RECORD
